{
  "id": "f6b16ba7-1e32-4278-948a-f823a79c2a35",
  "prevId": "00000000-0000-0000-0000-000000000000",
  "version": "7",
  "dialect": "postgresql",
  "tables": {
    "public.accounts": {
      "name": "accounts",
      "schema": "",
      "columns": {
        "id": {
          "name": "id",
          "type": "uuid",
          "primaryKey": true,
          "notNull": true,
          "default": "uuidv7()"
        },
        "user_id": {
          "name": "user_id",
          "type": "uuid",
          "primaryKey": false,
          "notNull": true
        },
        "type": {
          "name": "type",
          "type": "varchar(64)",
          "primaryKey": false,
          "notNull": true
        },
        "provider": {
          "name": "provider",
          "type": "varchar(128)",
          "primaryKey": false,
          "notNull": true
        },
        "provider_account_id": {
          "name": "provider_account_id",
          "type": "varchar(256)",
          "primaryKey": false,
          "notNull": true
        },
        "refresh_token": {
          "name": "refresh_token",
          "type": "text",
          "primaryKey": false,
          "notNull": false
        },
        "access_token": {
          "name": "access_token",
          "type": "text",
          "primaryKey": false,
          "notNull": false
        },
        "expires_at_ms": {
          "name": "expires_at_ms",
          "type": "bigint",
          "primaryKey": false,
          "notNull": false
        },
        "refresh_token_expires_at_ms": {
          "name": "refresh_token_expires_at_ms",
          "type": "bigint",
          "primaryKey": false,
          "notNull": false
        },
        "token_type": {
          "name": "token_type",
          "type": "varchar(64)",
          "primaryKey": false,
          "notNull": false
        },
        "scope": {
          "name": "scope",
          "type": "text",
          "primaryKey": false,
          "notNull": false
        },
        "id_token": {
          "name": "id_token",
          "type": "text",
          "primaryKey": false,
          "notNull": false
        },
        "session_state": {
          "name": "session_state",
          "type": "text",
          "primaryKey": false,
          "notNull": false
        }
      },
      "indexes": {
        "accounts_provider_provider_account_id_unique_idx": {
          "name": "accounts_provider_provider_account_id_unique_idx",
          "columns": [
            {
              "expression": "provider",
              "isExpression": false,
              "asc": true,
              "nulls": "last"
            },
            {
              "expression": "provider_account_id",
              "isExpression": false,
              "asc": true,
              "nulls": "last"
            }
          ],
          "isUnique": true,
          "concurrently": false,
          "method": "btree",
          "with": {}
        },
        "accounts_user_id_idx": {
          "name": "accounts_user_id_idx",
          "columns": [
            {
              "expression": "user_id",
              "isExpression": false,
              "asc": true,
              "nulls": "last"
            }
          ],
          "isUnique": false,
          "concurrently": false,
          "method": "btree",
          "with": {}
        }
      },
      "foreignKeys": {
        "accounts_user_id_users_id_fk": {
          "name": "accounts_user_id_users_id_fk",
          "tableFrom": "accounts",
          "tableTo": "users",
          "columnsFrom": [
            "user_id"
          ],
          "columnsTo": [
            "id"
          ],
          "onDelete": "cascade",
          "onUpdate": "no action"
        }
      },
      "compositePrimaryKeys": {},
      "uniqueConstraints": {},
      "policies": {},
      "checkConstraints": {},
      "isRLSEnabled": false
    },
    "public.sessions": {
      "name": "sessions",
      "schema": "",
      "columns": {
        "session_token": {
          "name": "session_token",
          "type": "varchar(256)",
          "primaryKey": true,
          "notNull": true
        },
        "user_id": {
          "name": "user_id",
          "type": "uuid",
          "primaryKey": false,
          "notNull": true
        },
        "expires_ms": {
          "name": "expires_ms",
          "type": "bigint",
          "primaryKey": false,
          "notNull": true
        }
      },
      "indexes": {},
      "foreignKeys": {
        "sessions_user_id_users_id_fk": {
          "name": "sessions_user_id_users_id_fk",
          "tableFrom": "sessions",
          "tableTo": "users",
          "columnsFrom": [
            "user_id"
          ],
          "columnsTo": [
            "id"
          ],
          "onDelete": "cascade",
          "onUpdate": "no action"
        }
      },
      "compositePrimaryKeys": {},
      "uniqueConstraints": {},
      "policies": {},
      "checkConstraints": {},
      "isRLSEnabled": false
    },
    "public.users": {
      "name": "users",
      "schema": "",
      "columns": {
        "id": {
          "name": "id",
          "type": "uuid",
          "primaryKey": true,
          "notNull": true,
          "default": "uuidv7()"
        },
        "name": {
          "name": "name",
          "type": "varchar(256)",
          "primaryKey": false,
          "notNull": false
        },
        "email": {
          "name": "email",
          "type": "varchar(320)",
          "primaryKey": false,
          "notNull": true
        },
        "email_verified_ms": {
          "name": "email_verified_ms",
          "type": "bigint",
          "primaryKey": false,
          "notNull": false
        },
        "image": {
          "name": "image",
          "type": "text",
          "primaryKey": false,
          "notNull": false
        },
        "target_percentile": {
          "name": "target_percentile",
          "type": "integer",
          "primaryKey": false,
          "notNull": false
        },
        "target_date_ms": {
          "name": "target_date_ms",
          "type": "bigint",
          "primaryKey": false,
          "notNull": false
        },
        "timer_prefs_json": {
          "name": "timer_prefs_json",
          "type": "jsonb",
          "primaryKey": false,
          "notNull": true,
          "default": "'{}'::jsonb"
        },
        "created_at_ms": {
          "name": "created_at_ms",
          "type": "bigint",
          "primaryKey": false,
          "notNull": true,
          "default": "(extract(epoch from now()) * 1000)::bigint"
        }
      },
      "indexes": {
        "users_email_idx": {
          "name": "users_email_idx",
          "columns": [
            {
              "expression": "email",
              "isExpression": false,
              "asc": true,
              "nulls": "last"
            }
          ],
          "isUnique": true,
          "concurrently": false,
          "method": "btree",
          "with": {}
        }
      },
      "foreignKeys": {},
      "compositePrimaryKeys": {},
      "uniqueConstraints": {},
      "policies": {},
      "checkConstraints": {},
      "isRLSEnabled": false
    },
    "public.verification_tokens": {
      "name": "verification_tokens",
      "schema": "",
      "columns": {
        "identifier": {
          "name": "identifier",
          "type": "varchar(320)",
          "primaryKey": false,
          "notNull": true
        },
        "token": {
          "name": "token",
          "type": "varchar(256)",
          "primaryKey": false,
          "notNull": true
        },
        "expires_ms": {
          "name": "expires_ms",
          "type": "bigint",
          "primaryKey": false,
          "notNull": true
        }
      },
      "indexes": {},
      "foreignKeys": {},
      "compositePrimaryKeys": {
        "verification_tokens_identifier_token_pk": {
          "name": "verification_tokens_identifier_token_pk",
          "columns": [
            "identifier",
            "token"
          ]
        }
      },
      "uniqueConstraints": {},
      "policies": {},
      "checkConstraints": {},
      "isRLSEnabled": false
    },
    "public.items": {
      "name": "items",
      "schema": "",
      "columns": {
        "id": {
          "name": "id",
          "type": "uuid",
          "primaryKey": true,
          "notNull": true,
          "default": "uuidv7()"
        },
        "sub_type_id": {
          "name": "sub_type_id",
          "type": "varchar(64)",
          "primaryKey": false,
          "notNull": true
        },
        "difficulty": {
          "name": "difficulty",
          "type": "item_difficulty",
          "typeSchema": "public",
          "primaryKey": false,
          "notNull": true
        },
        "source": {
          "name": "source",
          "type": "item_source",
          "typeSchema": "public",
          "primaryKey": false,
          "notNull": true
        },
        "status": {
          "name": "status",
          "type": "item_status",
          "typeSchema": "public",
          "primaryKey": false,
          "notNull": true,
          "default": "'candidate'"
        },
        "body": {
          "name": "body",
          "type": "jsonb",
          "primaryKey": false,
          "notNull": true
        },
        "options_json": {
          "name": "options_json",
          "type": "jsonb",
          "primaryKey": false,
          "notNull": true
        },
        "correct_answer": {
          "name": "correct_answer",
          "type": "varchar(64)",
          "primaryKey": false,
          "notNull": true
        },
        "explanation": {
          "name": "explanation",
          "type": "text",
          "primaryKey": false,
          "notNull": false
        },
        "strategy_id": {
          "name": "strategy_id",
          "type": "uuid",
          "primaryKey": false,
          "notNull": false
        },
        "embedding": {
          "name": "embedding",
          "type": "vector(1536)",
          "primaryKey": false,
          "notNull": false
        },
        "metadata_json": {
          "name": "metadata_json",
          "type": "jsonb",
          "primaryKey": false,
          "notNull": true,
          "default": "'{}'::jsonb"
        }
      },
      "indexes": {
        "items_sub_type_status_idx": {
          "name": "items_sub_type_status_idx",
          "columns": [
            {
              "expression": "sub_type_id",
              "isExpression": false,
              "asc": true,
              "nulls": "last"
            },
            {
              "expression": "status",
              "isExpression": false,
              "asc": true,
              "nulls": "last"
            }
          ],
          "isUnique": false,
          "concurrently": false,
          "method": "btree",
          "with": {}
        },
        "items_sub_type_difficulty_status_idx": {
          "name": "items_sub_type_difficulty_status_idx",
          "columns": [
            {
              "expression": "sub_type_id",
              "isExpression": false,
              "asc": true,
              "nulls": "last"
            },
            {
              "expression": "difficulty",
              "isExpression": false,
              "asc": true,
              "nulls": "last"
            },
            {
              "expression": "status",
              "isExpression": false,
              "asc": true,
              "nulls": "last"
            }
          ],
          "isUnique": false,
          "concurrently": false,
          "method": "btree",
          "with": {}
        }
      },
      "foreignKeys": {
        "items_sub_type_id_sub_types_id_fk": {
          "name": "items_sub_type_id_sub_types_id_fk",
          "tableFrom": "items",
          "tableTo": "sub_types",
          "columnsFrom": [
            "sub_type_id"
          ],
          "columnsTo": [
            "id"
          ],
          "onDelete": "no action",
          "onUpdate": "no action"
        },
        "items_strategy_id_strategies_id_fk": {
          "name": "items_strategy_id_strategies_id_fk",
          "tableFrom": "items",
          "tableTo": "strategies",
          "columnsFrom": [
            "strategy_id"
          ],
          "columnsTo": [
            "id"
          ],
          "onDelete": "no action",
          "onUpdate": "no action"
        }
      },
      "compositePrimaryKeys": {},
      "uniqueConstraints": {},
      "policies": {},
      "checkConstraints": {},
      "isRLSEnabled": false
    },
    "public.strategies": {
      "name": "strategies",
      "schema": "",
      "columns": {
        "id": {
          "name": "id",
          "type": "uuid",
          "primaryKey": true,
          "notNull": true,
          "default": "uuidv7()"
        },
        "sub_type_id": {
          "name": "sub_type_id",
          "type": "varchar(64)",
          "primaryKey": false,
          "notNull": true
        },
        "kind": {
          "name": "kind",
          "type": "strategy_kind",
          "typeSchema": "public",
          "primaryKey": false,
          "notNull": true
        },
        "text": {
          "name": "text",
          "type": "text",
          "primaryKey": false,
          "notNull": true
        }
      },
      "indexes": {
        "strategies_sub_type_idx": {
          "name": "strategies_sub_type_idx",
          "columns": [
            {
              "expression": "sub_type_id",
              "isExpression": false,
              "asc": true,
              "nulls": "last"
            }
          ],
          "isUnique": false,
          "concurrently": false,
          "method": "btree",
          "with": {}
        }
      },
      "foreignKeys": {
        "strategies_sub_type_id_sub_types_id_fk": {
          "name": "strategies_sub_type_id_sub_types_id_fk",
          "tableFrom": "strategies",
          "tableTo": "sub_types",
          "columnsFrom": [
            "sub_type_id"
          ],
          "columnsTo": [
            "id"
          ],
          "onDelete": "no action",
          "onUpdate": "no action"
        }
      },
      "compositePrimaryKeys": {},
      "uniqueConstraints": {},
      "policies": {},
      "checkConstraints": {},
      "isRLSEnabled": false
    },
    "public.sub_types": {
      "name": "sub_types",
      "schema": "",
      "columns": {
        "id": {
          "name": "id",
          "type": "varchar(64)",
          "primaryKey": true,
          "notNull": true
        },
        "name": {
          "name": "name",
          "type": "varchar(128)",
          "primaryKey": false,
          "notNull": true
        },
        "section": {
          "name": "section",
          "type": "sub_type_section",
          "typeSchema": "public",
          "primaryKey": false,
          "notNull": true
        },
        "latency_threshold_ms": {
          "name": "latency_threshold_ms",
          "type": "bigint",
          "primaryKey": false,
          "notNull": true
        }
      },
      "indexes": {},
      "foreignKeys": {},
      "compositePrimaryKeys": {},
      "uniqueConstraints": {},
      "policies": {},
      "checkConstraints": {},
      "isRLSEnabled": false
    },
    "public.candidate_promotion_log": {
      "name": "candidate_promotion_log",
      "schema": "",
      "columns": {
        "id": {
          "name": "id",
          "type": "uuid",
          "primaryKey": true,
          "notNull": true,
          "default": "uuidv7()"
        },
        "item_id": {
          "name": "item_id",
          "type": "uuid",
          "primaryKey": false,
          "notNull": true
        },
        "decision": {
          "name": "decision",
          "type": "promotion_decision",
          "typeSchema": "public",
          "primaryKey": false,
          "notNull": true
        },
        "observed_attempts": {
          "name": "observed_attempts",
          "type": "integer",
          "primaryKey": false,
          "notNull": true
        },
        "observed_accuracy": {
          "name": "observed_accuracy",
          "type": "real",
          "primaryKey": false,
          "notNull": true
        },
        "observed_median_latency_ms": {
          "name": "observed_median_latency_ms",
          "type": "integer",
          "primaryKey": false,
          "notNull": true
        },
        "decision_reason": {
          "name": "decision_reason",
          "type": "text",
          "primaryKey": false,
          "notNull": false
        },
        "enforced": {
          "name": "enforced",
          "type": "boolean",
          "primaryKey": false,
          "notNull": true,
          "default": false
        },
        "decided_at_ms": {
          "name": "decided_at_ms",
          "type": "bigint",
          "primaryKey": false,
          "notNull": true
        }
      },
      "indexes": {
        "candidate_promotion_log_item_id_idx": {
          "name": "candidate_promotion_log_item_id_idx",
          "columns": [
            {
              "expression": "item_id",
              "isExpression": false,
              "asc": true,
              "nulls": "last"
            }
          ],
          "isUnique": false,
          "concurrently": false,
          "method": "btree",
          "with": {}
        },
        "candidate_promotion_log_decided_at_idx": {
          "name": "candidate_promotion_log_decided_at_idx",
          "columns": [
            {
              "expression": "decided_at_ms",
              "isExpression": false,
              "asc": true,
              "nulls": "last"
            }
          ],
          "isUnique": false,
          "concurrently": false,
          "method": "btree",
          "with": {}
        }
      },
      "foreignKeys": {
        "candidate_promotion_log_item_id_items_id_fk": {
          "name": "candidate_promotion_log_item_id_items_id_fk",
          "tableFrom": "candidate_promotion_log",
          "tableTo": "items",
          "columnsFrom": [
            "item_id"
          ],
          "columnsTo": [
            "id"
          ],
          "onDelete": "no action",
          "onUpdate": "no action"
        }
      },
      "compositePrimaryKeys": {},
      "uniqueConstraints": {},
      "policies": {},
      "checkConstraints": {},
      "isRLSEnabled": false
    },
    "public.strategy_views": {
      "name": "strategy_views",
      "schema": "",
      "columns": {
        "id": {
          "name": "id",
          "type": "uuid",
          "primaryKey": true,
          "notNull": true,
          "default": "uuidv7()"
        },
        "user_id": {
          "name": "user_id",
          "type": "uuid",
          "primaryKey": false,
          "notNull": true
        },
        "strategy_id": {
          "name": "strategy_id",
          "type": "uuid",
          "primaryKey": false,
          "notNull": true
        },
        "viewed_at_ms": {
          "name": "viewed_at_ms",
          "type": "bigint",
          "primaryKey": false,
          "notNull": true
        }
      },
      "indexes": {
        "strategy_views_user_strategy_idx": {
          "name": "strategy_views_user_strategy_idx",
          "columns": [
            {
              "expression": "user_id",
              "isExpression": false,
              "asc": true,
              "nulls": "last"
            },
            {
              "expression": "strategy_id",
              "isExpression": false,
              "asc": true,
              "nulls": "last"
            }
          ],
          "isUnique": false,
          "concurrently": false,
          "method": "btree",
          "with": {}
        }
      },
      "foreignKeys": {
        "strategy_views_user_id_users_id_fk": {
          "name": "strategy_views_user_id_users_id_fk",
          "tableFrom": "strategy_views",
          "tableTo": "users",
          "columnsFrom": [
            "user_id"
          ],
          "columnsTo": [
            "id"
          ],
          "onDelete": "cascade",
          "onUpdate": "no action"
        },
        "strategy_views_strategy_id_strategies_id_fk": {
          "name": "strategy_views_strategy_id_strategies_id_fk",
          "tableFrom": "strategy_views",
          "tableTo": "strategies",
          "columnsFrom": [
            "strategy_id"
          ],
          "columnsTo": [
            "id"
          ],
          "onDelete": "cascade",
          "onUpdate": "no action"
        }
      },
      "compositePrimaryKeys": {},
      "uniqueConstraints": {},
      "policies": {},
      "checkConstraints": {},
      "isRLSEnabled": false
    },
    "public.attempts": {
      "name": "attempts",
      "schema": "",
      "columns": {
        "id": {
          "name": "id",
          "type": "uuid",
          "primaryKey": true,
          "notNull": true,
          "default": "uuidv7()"
        },
        "session_id": {
          "name": "session_id",
          "type": "uuid",
          "primaryKey": false,
          "notNull": true
        },
        "item_id": {
          "name": "item_id",
          "type": "uuid",
          "primaryKey": false,
          "notNull": true
        },
        "selected_answer": {
          "name": "selected_answer",
          "type": "varchar(64)",
          "primaryKey": false,
          "notNull": false
        },
        "correct": {
          "name": "correct",
          "type": "boolean",
          "primaryKey": false,
          "notNull": true
        },
        "latency_ms": {
          "name": "latency_ms",
          "type": "integer",
          "primaryKey": false,
          "notNull": true
        },
        "served_at_tier": {
          "name": "served_at_tier",
          "type": "item_difficulty",
          "typeSchema": "public",
          "primaryKey": false,
          "notNull": true
        },
        "fallback_from_tier": {
          "name": "fallback_from_tier",
          "type": "item_difficulty",
          "typeSchema": "public",
          "primaryKey": false,
          "notNull": false
        },
        "triage_prompt_fired": {
          "name": "triage_prompt_fired",
          "type": "boolean",
          "primaryKey": false,
          "notNull": true,
          "default": false
        },
        "triage_taken": {
          "name": "triage_taken",
          "type": "boolean",
          "primaryKey": false,
          "notNull": true,
          "default": false
        },
        "metadata_json": {
          "name": "metadata_json",
          "type": "jsonb",
          "primaryKey": false,
          "notNull": true,
          "default": "'{}'::jsonb"
        }
      },
      "indexes": {
        "attempts_session_id_idx": {
          "name": "attempts_session_id_idx",
          "columns": [
            {
              "expression": "session_id",
              "isExpression": false,
              "asc": true,
              "nulls": "last"
            }
          ],
          "isUnique": false,
          "concurrently": false,
          "method": "btree",
          "with": {}
        },
        "attempts_item_id_idx": {
          "name": "attempts_item_id_idx",
          "columns": [
            {
              "expression": "item_id",
              "isExpression": false,
              "asc": true,
              "nulls": "last"
            }
          ],
          "isUnique": false,
          "concurrently": false,
          "method": "btree",
          "with": {}
        }
      },
      "foreignKeys": {
        "attempts_session_id_practice_sessions_id_fk": {
          "name": "attempts_session_id_practice_sessions_id_fk",
          "tableFrom": "attempts",
          "tableTo": "practice_sessions",
          "columnsFrom": [
            "session_id"
          ],
          "columnsTo": [
            "id"
          ],
          "onDelete": "cascade",
          "onUpdate": "no action"
        },
        "attempts_item_id_items_id_fk": {
          "name": "attempts_item_id_items_id_fk",
          "tableFrom": "attempts",
          "tableTo": "items",
          "columnsFrom": [
            "item_id"
          ],
          "columnsTo": [
            "id"
          ],
          "onDelete": "no action",
          "onUpdate": "no action"
        }
      },
      "compositePrimaryKeys": {},
      "uniqueConstraints": {},
      "policies": {},
      "checkConstraints": {},
      "isRLSEnabled": false
    },
    "public.mastery_state": {
      "name": "mastery_state",
      "schema": "",
      "columns": {
        "user_id": {
          "name": "user_id",
          "type": "uuid",
          "primaryKey": false,
          "notNull": true
        },
        "sub_type_id": {
          "name": "sub_type_id",
          "type": "varchar(64)",
          "primaryKey": false,
          "notNull": true
        },
        "current_state": {
          "name": "current_state",
          "type": "mastery_level",
          "typeSchema": "public",
          "primaryKey": false,
          "notNull": true
        },
        "was_mastered": {
          "name": "was_mastered",
          "type": "boolean",
          "primaryKey": false,
          "notNull": true,
          "default": false
        },
        "updated_at_ms": {
          "name": "updated_at_ms",
          "type": "bigint",
          "primaryKey": false,
          "notNull": true
        }
      },
      "indexes": {},
      "foreignKeys": {
        "mastery_state_user_id_users_id_fk": {
          "name": "mastery_state_user_id_users_id_fk",
          "tableFrom": "mastery_state",
          "tableTo": "users",
          "columnsFrom": [
            "user_id"
          ],
          "columnsTo": [
            "id"
          ],
          "onDelete": "cascade",
          "onUpdate": "no action"
        },
        "mastery_state_sub_type_id_sub_types_id_fk": {
          "name": "mastery_state_sub_type_id_sub_types_id_fk",
          "tableFrom": "mastery_state",
          "tableTo": "sub_types",
          "columnsFrom": [
            "sub_type_id"
          ],
          "columnsTo": [
            "id"
          ],
          "onDelete": "no action",
          "onUpdate": "no action"
        }
      },
      "compositePrimaryKeys": {
        "mastery_state_user_sub_type_pk": {
          "name": "mastery_state_user_sub_type_pk",
          "columns": [
            "user_id",
            "sub_type_id"
          ]
        }
      },
      "uniqueConstraints": {},
      "policies": {},
      "checkConstraints": {},
      "isRLSEnabled": false
    },
    "public.practice_sessions": {
      "name": "practice_sessions",
      "schema": "",
      "columns": {
        "id": {
          "name": "id",
          "type": "uuid",
          "primaryKey": true,
          "notNull": true,
          "default": "uuidv7()"
        },
        "user_id": {
          "name": "user_id",
          "type": "uuid",
          "primaryKey": false,
          "notNull": true
        },
        "type": {
          "name": "type",
          "type": "session_type",
          "typeSchema": "public",
          "primaryKey": false,
          "notNull": true
        },
        "sub_type_id": {
          "name": "sub_type_id",
          "type": "varchar(64)",
          "primaryKey": false,
          "notNull": false
        },
        "timer_mode": {
          "name": "timer_mode",
          "type": "timer_mode",
          "typeSchema": "public",
          "primaryKey": false,
          "notNull": false
        },
        "target_question_count": {
          "name": "target_question_count",
          "type": "integer",
          "primaryKey": false,
          "notNull": true
        },
        "started_at_ms": {
          "name": "started_at_ms",
          "type": "bigint",
          "primaryKey": false,
          "notNull": true
        },
        "ended_at_ms": {
          "name": "ended_at_ms",
          "type": "bigint",
          "primaryKey": false,
          "notNull": false
        },
        "last_heartbeat_ms": {
          "name": "last_heartbeat_ms",
          "type": "bigint",
          "primaryKey": false,
          "notNull": true,
          "default": "(extract(epoch from now()) * 1000)::bigint"
        },
        "completion_reason": {
          "name": "completion_reason",
          "type": "completion_reason",
          "typeSchema": "public",
          "primaryKey": false,
          "notNull": false
        },
        "narrowing_ramp_completed": {
          "name": "narrowing_ramp_completed",
          "type": "boolean",
          "primaryKey": false,
          "notNull": true,
          "default": false
        },
        "if_then_plan": {
          "name": "if_then_plan",
          "type": "text",
          "primaryKey": false,
          "notNull": false
        },
        "recency_excluded_item_ids": {
          "name": "recency_excluded_item_ids",
          "type": "uuid[]",
          "primaryKey": false,
          "notNull": true,
          "default": "'{}'::uuid[]"
        },
        "strategy_review_viewed": {
          "name": "strategy_review_viewed",
          "type": "boolean",
          "primaryKey": false,
          "notNull": true,
          "default": false
        },
        "diagnostic_overtime_note_shown_at_ms": {
          "name": "diagnostic_overtime_note_shown_at_ms",
          "type": "bigint",
          "primaryKey": false,
          "notNull": false
        }
      },
      "indexes": {
        "practice_sessions_user_id_idx": {
          "name": "practice_sessions_user_id_idx",
          "columns": [
            {
              "expression": "user_id",
              "isExpression": false,
              "asc": true,
              "nulls": "last"
            }
          ],
          "isUnique": false,
          "concurrently": false,
          "method": "btree",
          "with": {}
        },
        "practice_sessions_user_type_ended_idx": {
          "name": "practice_sessions_user_type_ended_idx",
          "columns": [
            {
              "expression": "user_id",
              "isExpression": false,
              "asc": true,
              "nulls": "last"
            },
            {
              "expression": "type",
              "isExpression": false,
              "asc": true,
              "nulls": "last"
            },
            {
              "expression": "ended_at_ms",
              "isExpression": false,
              "asc": true,
              "nulls": "last"
            }
          ],
          "isUnique": false,
          "concurrently": false,
          "method": "btree",
          "with": {}
        },
        "practice_sessions_abandon_sweep_idx": {
          "name": "practice_sessions_abandon_sweep_idx",
          "columns": [
            {
              "expression": "last_heartbeat_ms",
              "isExpression": false,
              "asc": true,
              "nulls": "last"
            }
          ],
          "isUnique": false,
          "where": "\"practice_sessions\".\"ended_at_ms\" IS NULL",
          "concurrently": false,
          "method": "btree",
          "with": {}
        },
        "practice_sessions_recency_excluded_gin_idx": {
          "name": "practice_sessions_recency_excluded_gin_idx",
          "columns": [
            {
              "expression": "recency_excluded_item_ids",
              "isExpression": false,
              "asc": true,
              "nulls": "last"
            }
          ],
          "isUnique": false,
          "concurrently": false,
          "method": "gin",
          "with": {}
        }
      },
      "foreignKeys": {
        "practice_sessions_user_id_users_id_fk": {
          "name": "practice_sessions_user_id_users_id_fk",
          "tableFrom": "practice_sessions",
          "tableTo": "users",
          "columnsFrom": [
            "user_id"
          ],
          "columnsTo": [
            "id"
          ],
          "onDelete": "cascade",
          "onUpdate": "no action"
        },
        "practice_sessions_sub_type_id_sub_types_id_fk": {
          "name": "practice_sessions_sub_type_id_sub_types_id_fk",
          "tableFrom": "practice_sessions",
          "tableTo": "sub_types",
          "columnsFrom": [
            "sub_type_id"
          ],
          "columnsTo": [
            "id"
          ],
          "onDelete": "no action",
          "onUpdate": "no action"
        }
      },
      "compositePrimaryKeys": {},
      "uniqueConstraints": {},
      "policies": {},
      "checkConstraints": {},
      "isRLSEnabled": false
    },
    "public.review_queue": {
      "name": "review_queue",
      "schema": "",
      "columns": {
        "id": {
          "name": "id",
          "type": "uuid",
          "primaryKey": true,
          "notNull": true,
          "default": "uuidv7()"
        },
        "user_id": {
          "name": "user_id",
          "type": "uuid",
          "primaryKey": false,
          "notNull": true
        },
        "item_id": {
          "name": "item_id",
          "type": "uuid",
          "primaryKey": false,
          "notNull": true
        },
        "due_at_ms": {
          "name": "due_at_ms",
          "type": "bigint",
          "primaryKey": false,
          "notNull": true
        },
        "interval_days": {
          "name": "interval_days",
          "type": "integer",
          "primaryKey": false,
          "notNull": true
        }
      },
      "indexes": {
        "review_queue_user_due_idx": {
          "name": "review_queue_user_due_idx",
          "columns": [
            {
              "expression": "user_id",
              "isExpression": false,
              "asc": true,
              "nulls": "last"
            },
            {
              "expression": "due_at_ms",
              "isExpression": false,
              "asc": true,
              "nulls": "last"
            }
          ],
          "isUnique": false,
          "concurrently": false,
          "method": "btree",
          "with": {}
        },
        "review_queue_user_item_unique": {
          "name": "review_queue_user_item_unique",
          "columns": [
            {
              "expression": "user_id",
              "isExpression": false,
              "asc": true,
              "nulls": "last"
            },
            {
              "expression": "item_id",
              "isExpression": false,
              "asc": true,
              "nulls": "last"
            }
          ],
          "isUnique": true,
          "concurrently": false,
          "method": "btree",
          "with": {}
        }
      },
      "foreignKeys": {
        "review_queue_user_id_users_id_fk": {
          "name": "review_queue_user_id_users_id_fk",
          "tableFrom": "review_queue",
          "tableTo": "users",
          "columnsFrom": [
            "user_id"
          ],
          "columnsTo": [
            "id"
          ],
          "onDelete": "cascade",
          "onUpdate": "no action"
        },
        "review_queue_item_id_items_id_fk": {
          "name": "review_queue_item_id_items_id_fk",
          "tableFrom": "review_queue",
          "tableTo": "items",
          "columnsFrom": [
            "item_id"
          ],
          "columnsTo": [
            "id"
          ],
          "onDelete": "no action",
          "onUpdate": "no action"
        }
      },
      "compositePrimaryKeys": {},
      "uniqueConstraints": {},
      "policies": {},
      "checkConstraints": {},
      "isRLSEnabled": false
    }
  },
  "enums": {
    "public.item_difficulty": {
      "name": "item_difficulty",
      "schema": "public",
      "values": [
        "easy",
        "medium",
        "hard",
        "brutal"
      ]
    },
    "public.item_source": {
      "name": "item_source",
      "schema": "public",
      "values": [
        "real",
        "generated"
      ]
    },
    "public.item_status": {
      "name": "item_status",
      "schema": "public",
      "values": [
        "live",
        "candidate",
        "retired"
      ]
    },
    "public.strategy_kind": {
      "name": "strategy_kind",
      "schema": "public",
      "values": [
        "recognition",
        "technique",
        "trap"
      ]
    },
    "public.sub_type_section": {
      "name": "sub_type_section",
      "schema": "public",
      "values": [
        "verbal",
        "numerical"
      ]
    },
    "public.promotion_decision": {
      "name": "promotion_decision",
      "schema": "public",
      "values": [
        "promote",
        "retire",
        "hold"
      ]
    },
    "public.mastery_level": {
      "name": "mastery_level",
      "schema": "public",
      "values": [
        "learning",
        "fluent",
        "mastered",
        "decayed"
      ]
    },
    "public.completion_reason": {
      "name": "completion_reason",
      "schema": "public",
      "values": [
        "completed",
        "abandoned"
      ]
    },
    "public.session_type": {
      "name": "session_type",
      "schema": "public",
      "values": [
        "diagnostic",
        "drill",
        "full_length",
        "simulation",
        "review"
      ]
    },
    "public.timer_mode": {
      "name": "timer_mode",
      "schema": "public",
      "values": [
        "standard",
        "speed_ramp",
        "brutal"
      ]
    }
  },
  "schemas": {},
  "sequences": {},
  "roles": {},
  "policies": {},
  "views": {},
  "_meta": {
    "columns": {},
    "schemas": {},
    "tables": {}
  }
}